survlimepy/__init__.py
survlimepy/load_datasets.py
survlimepy/survlime_explainer.py
survlimepy/datasets/__init__.py
survlimepy/datasets/loading_utils.py
survlimepy/datasets/lung_dataset.csv
survlimepy/datasets/udca_dataset.csv
survlimepy/datasets/veteran.csv
survlimepy/utils/__init__.py
survlimepy/utils/neighbours_generator.py
survlimepy/utils/optimisation.py
survlimepy/utils/predict.py
survlimepy/utils/step_function.py
survlimepy-0.0.11.dist-info/LICENSE
survlimepy-0.0.11.dist-info/METADATA
survlimepy-0.0.11.dist-info/WHEEL
survlimepy-0.0.11.dist-info/top_level.txt
survlimepy-0.0.11.dist-info/RECORD
