Metadata-Version: 2.1
Name: survlimepy
Version: 0.0.11
Summary: A python package implementing SurvLIME algorithm
Author-email: Carlos Hernández Pérez <crherperez95@gmail.com>, Cristian Pachón García <cc.pachon@gmail.com>
License: GNU GENERAL PUBLIC LICENSE
Project-URL: documentation, https://github.com/imatge-upc/SurvLIMEpy
Project-URL: repository, https://github.com/imatge-upc/SurvLIMEpy
Keywords: Interpretable Machine Learning,eXplainalbe Artificial Intelligence,Survival Analysis,Machine Learning,Python
Classifier: License :: OSI Approved :: GNU General Public License v3 or later (GPLv3+)
Requires-Python: >=3.8
License-File: LICENSE
Requires-Dist: numpy
Requires-Dist: cvxpy
Requires-Dist: scikit-survival (==0.18.0)
Requires-Dist: scikit-learn (==1.1.2)
Requires-Dist: pandas
Requires-Dist: tqdm
Requires-Dist: seaborn
Requires-Dist: matplotlib
Provides-Extra: dev
Requires-Dist: pytest ; extra == 'dev'
Requires-Dist: black ; extra == 'dev'
